shim/__init__.py
shim/shim.py
mcp_sse_shim-0.1.27.dist-info/METADATA
mcp_sse_shim-0.1.27.dist-info/WHEEL
mcp_sse_shim-0.1.27.dist-info/entry_points.txt
mcp_sse_shim-0.1.27.dist-info/RECORD
