Metadata-Version: 2.4
Name: mcp-sse-shim
Version: 0.1.27
Summary: shim for mcp sse over stdio
Requires-Python: >=3.9
Requires-Dist: aiohttp>=3.11.10
